fastemc/__init__.py
fastemc/__main__.py
fastemc/fastemc.py
fastemc-0.0.6.dist-info/LICENSE
fastemc-0.0.6.dist-info/METADATA
fastemc-0.0.6.dist-info/WHEEL
fastemc-0.0.6.dist-info/top_level.txt
fastemc-0.0.6.dist-info/RECORD
