Metadata-Version: 2.1
Name: fastemc
Version: 0.0.6
Summary: FastEMC is a method for dimensionality reduction.
Home-page: https://github.com/rowland-208/fastemc
Author: James Rowland
Author-email: rowland.208@gmail.com
License: UNKNOWN
Platform: UNKNOWN
Requires-Python: >=2.7
Requires-Dist: numpy
Requires-Dist: pandas
Requires-Dist: scikit-learn
Requires-Dist: tqdm
